Kuat/__init__.py
anam_sipaling_tersakiti-0.1.0.dist-info/METADATA
anam_sipaling_tersakiti-0.1.0.dist-info/WHEEL
anam_sipaling_tersakiti-0.1.0.dist-info/top_level.txt
anam_sipaling_tersakiti-0.1.0.dist-info/RECORD
