Metadata-Version: 2.4
Name: anam_sipaling_tersakiti
Version: 0.1.0
Summary:  Ini COntoh upload Library
Author: Anam
Author-email: anam@contoh.com
Classifier: Programming Language :: Python :: 3
Classifier: License :: OSI Approved :: MIT License
Requires-Python: >=3.6
Dynamic: author
Dynamic: author-email
Dynamic: classifier
Dynamic: description
Dynamic: description-content-type
Dynamic: requires-python
Dynamic: summary
